{
  "locked": false,
  "version": 2,
  "targets": {
    ".NETPortable,Version=v4.5,Profile=Profile111": {
      "Manatee.Trello/1.15.0.1": {
        "type": "package",
        "compile": {
          "lib/portable-net45+netcore45+wpa81/Manatee.Trello.dll": {}
        },
        "runtime": {
          "lib/portable-net45+netcore45+wpa81/Manatee.Trello.dll": {}
        }
      }
    }
  },
  "libraries": {
    "Manatee.Trello/1.15.0.1": {
      "sha512": "7I7M9oUTK1Ki460b3aM5EKDH1ucJ/ahkIpWDtdxUfn6gxSrXIT3BLGJbu8RSKb0m/OHZPmWxtLhAHTOAioZTIA==",
      "type": "package",
      "path": "Manatee.Trello/1.15.0.1",
      "files": [
        "Manatee.Trello.1.15.0.1.nupkg.sha512",
        "Manatee.Trello.nuspec",
        "lib/MonoAndroid/Manatee.Trello.XML",
        "lib/MonoAndroid/Manatee.Trello.dll",
        "lib/MonoAndroid/Manatee.Trello.pdb",
        "lib/MonoMac/Manatee.Trello.XML",
        "lib/MonoMac/Manatee.Trello.dll",
        "lib/MonoMac/Manatee.Trello.pdb",
        "lib/MonoTouch/Manatee.Trello.XML",
        "lib/MonoTouch/Manatee.Trello.dll",
        "lib/MonoTouch/Manatee.Trello.pdb",
        "lib/net35-client/Manatee.Trello.XML",
        "lib/net35-client/Manatee.Trello.dll",
        "lib/net35-client/Manatee.Trello.pdb",
        "lib/net40-client/Manatee.Trello.XML",
        "lib/net40-client/Manatee.Trello.dll",
        "lib/net40-client/Manatee.Trello.pdb",
        "lib/net45/Manatee.Trello.dll",
        "lib/net45/Manatee.Trello.pdb",
        "lib/net45/Manatee.Trello.xml",
        "lib/netstandard1.6/Manatee.Trello.dll",
        "lib/netstandard1.6/Manatee.Trello.pdb",
        "lib/netstandard1.6/Manatee.Trello.xml",
        "lib/portable-net45+netcore45+wpa81/Manatee.Trello.XML",
        "lib/portable-net45+netcore45+wpa81/Manatee.Trello.dll",
        "lib/portable-net45+netcore45+wpa81/Manatee.Trello.pdb"
      ]
    }
  },
  "projectFileDependencyGroups": {
    "": [
      "Manatee.Trello >= 1.15.0.1"
    ],
    ".NETPortable,Version=v4.5,Profile=Profile111": []
  },
  "tools": {},
  "projectFileToolGroups": {}
}